databind/core/__init__.py
databind/core/context.py
databind/core/converter.py
databind/core/dataclasses.py
databind/core/dataclasses.pyi
databind/core/mapper.py
databind/core/py.typed
databind/core/schema.py
databind/core/settings.py
databind/core/tests/context_test.py
databind/core/tests/schema_docspec_example_test.py
databind/core/tests/schema_test.py
databind/core/tests/schema_with_nested_dataclasses_test.py
databind/core/union.py
databind/core/utils.py
databind/json/__init__.py
databind/json/converters.py
databind/json/module.py
databind/json/py.typed
databind/json/settings.py
databind/json/tests/converters_test.py
databind-4.5.1.dist-info/METADATA
databind-4.5.1.dist-info/WHEEL
databind-4.5.1.dist-info/RECORD
